sized_cacher.py
sized_cacher-1.1.dist-info/DESCRIPTION.rst
sized_cacher-1.1.dist-info/METADATA
sized_cacher-1.1.dist-info/RECORD
sized_cacher-1.1.dist-info/WHEEL
sized_cacher-1.1.dist-info/entry_points.txt
sized_cacher-1.1.dist-info/metadata.json
sized_cacher-1.1.dist-info/top_level.txt
