Metadata-Version: 2.0
Name: sized-cacher
Version: 1.1
Summary: cache results of function call with expire and maxsize.
Home-page: https://github.com/weaming/sized-cacher
Author: weaming
Author-email: garden.yuen@gmail.com
License: UNKNOWN
Project-URL: Source, https://github.com/weaming/sized-cacher
Project-URL: Bug Reports, https://github.com/weaming/sized-cacher
Keywords: math
Platform: UNKNOWN
